{
  "basic_farm": {
    "id": "basic_farm",
    "name": "Starter Farm",
    "description": "Boosts crop growth around it and produces a little food over time.",
    "type": "production",
    "category": "farm",
    "cost": {
      "wood": 40,
      "stone": 20
    },
    "effects": {
      "crop_growth_speed": 1.2
    },
    "upgradePath": ["advanced_farm"],
    "buildTime": 2,
    "width": 2,
    "height": 2
  },
  "advanced_farm": {
    "id": "advanced_farm",
    "name": "Hydro Farm",
    "description": "A stronger farm module unlocked by agriculture research.",
    "type": "production",
    "category": "farm",
    "cost": {
      "wood": 80,
      "stone": 50,
      "metal": 30
    },
    "effects": {
      "crop_growth_speed": 1.5,
      "crop_yield": 1.2
    },
    "upgradePath": ["super_farm"],
    "buildTime": 3,
    "width": 2,
    "height": 2
  },
  "super_farm": {
    "id": "super_farm",
    "name": "Gene Farm",
    "description": "Late-game farm with strong food and growth output.",
    "type": "production",
    "category": "farm",
    "cost": {
      "wood": 140,
      "stone": 90,
      "metal": 90,
      "energy": 50
    },
    "effects": {
      "crop_growth_speed": 2.0,
      "crop_yield": 1.5
    },
    "buildTime": 5,
    "width": 3,
    "height": 3
  },
  "basic_mine": {
    "id": "basic_mine",
    "name": "Extractor",
    "description": "Produces stone and metal from the surrounding alien crust.",
    "type": "production",
    "category": "mine",
    "cost": {
      "wood": 70,
      "stone": 60
    },
    "effects": {
      "mining_speed": 1.0
    },
    "upgradePath": ["advanced_mine"],
    "buildTime": 3,
    "width": 2,
    "height": 2
  },
  "advanced_mine": {
    "id": "advanced_mine",
    "name": "Deep Extractor",
    "description": "A more efficient extractor unlocked by industry research.",
    "type": "production",
    "category": "mine",
    "cost": {
      "wood": 110,
      "stone": 120,
      "metal": 80
    },
    "effects": {
      "mining_speed": 1.5
    },
    "upgradePath": ["super_mine"],
    "buildTime": 4,
    "width": 2,
    "height": 2
  },
  "super_mine": {
    "id": "super_mine",
    "name": "Quantum Extractor",
    "description": "Late-game extractor with very strong metal output.",
    "type": "production",
    "category": "mine",
    "cost": {
      "wood": 180,
      "stone": 180,
      "metal": 160,
      "energy": 100
    },
    "effects": {
      "mining_speed": 2.0
    },
    "buildTime": 6,
    "width": 3,
    "height": 3
  },
  "machine_gun_turret": {
    "id": "machine_gun_turret",
    "name": "Auto Turret",
    "description": "Cheap all-purpose defense against early waves.",
    "type": "defense",
    "category": "turret",
    "cost": {
      "wood": 25,
      "stone": 20,
      "metal": 30
    },
    "effects": {
      "damage": 16,
      "range": 110,
      "fire_rate": 3.5
    },
    "buildTime": 1,
    "width": 1,
    "height": 1
  },
  "laser_turret": {
    "id": "laser_turret",
    "name": "Laser Turret",
    "description": "High damage tower unlocked by weapons research.",
    "type": "defense",
    "category": "turret",
    "cost": {
      "wood": 45,
      "stone": 30,
      "metal": 50,
      "energy": 20
    },
    "effects": {
      "damage": 45,
      "range": 150,
      "fire_rate": 1.0
    },
    "buildTime": 2,
    "width": 1,
    "height": 1
  },
  "rocket_launcher": {
    "id": "rocket_launcher",
    "name": "Rocket Pod",
    "description": "Heavy defense with high damage and long range.",
    "type": "defense",
    "category": "turret",
    "cost": {
      "wood": 70,
      "stone": 40,
      "metal": 100,
      "energy": 40
    },
    "effects": {
      "damage": 80,
      "range": 200,
      "fire_rate": 0.5
    },
    "buildTime": 3,
    "width": 2,
    "height": 2
  },
  "wall": {
    "id": "wall",
    "name": "Barrier Wall",
    "description": "Simple blocking defense used to delay enemies.",
    "type": "defense",
    "category": "wall",
    "cost": {
      "stone": 15
    },
    "effects": {
      "health": 220
    },
    "buildTime": 1,
    "width": 1,
    "height": 1
  },
  "command_center": {
    "id": "command_center",
    "name": "Command Core",
    "description": "The colony heart. Lose it and the run ends.",
    "type": "function",
    "category": "core",
    "cost": {
      "wood": 200,
      "stone": 150,
      "metal": 100
    },
    "effects": {
      "health": 600,
      "building_limit": 10
    },
    "buildTime": 5,
    "width": 3,
    "height": 3
  },
  "resource_depot": {
    "id": "resource_depot",
    "name": "Depot",
    "description": "Expands your economy and gives a small energy trickle.",
    "type": "function",
    "category": "storage",
    "cost": {
      "wood": 90,
      "stone": 70
    },
    "effects": {
      "storage_capacity": 500
    },
    "buildTime": 2,
    "width": 2,
    "height": 2
  },
  "medical_bay": {
    "id": "medical_bay",
    "name": "Med Bay",
    "description": "Stabilizes survivors and slowly restores colony integrity.",
    "type": "function",
    "category": "support",
    "cost": {
      "wood": 120,
      "metal": 80,
      "energy": 40
    },
    "effects": {
      "healing_rate": 10
    },
    "buildTime": 3,
    "width": 2,
    "height": 2
  },
  "communication_tower": {
    "id": "communication_tower",
    "name": "Relay Tower",
    "description": "Extends awareness and adds a little passive energy.",
    "type": "function",
    "category": "support",
    "cost": {
      "wood": 70,
      "metal": 60,
      "energy": 30
    },
    "effects": {
      "detection_range": 200
    },
    "buildTime": 2,
    "width": 1,
    "height": 3
  },
  "trading_post": {
    "id": "trading_post",
    "name": "Exchange Post",
    "description": "Converts food into research by processing xenobiological samples.",
    "type": "function",
    "category": "support",
    "cost": {
      "wood": 120,
      "stone": 90,
      "metal": 80
    },
    "effects": {
      "trading_efficiency": 1.2
    },
    "buildTime": 4,
    "width": 2,
    "height": 2
  }
}
